justhacking/__init__.py
justhacking/__main__.py
justhacking/jh_cmdcenter.py
justhacking/jh_matrix.py
justhacking/justhacking.py
justhacking-2.0.9.dist-info/METADATA
justhacking-2.0.9.dist-info/WHEEL
justhacking-2.0.9.dist-info/entry_points.txt
justhacking-2.0.9.dist-info/top_level.txt
justhacking-2.0.9.dist-info/RECORD
