Metadata-Version: 2.1
Name: justhacking
Version: 2.0.9
Summary: Just Hacking is a Python CLI script that stimulates as you are hacking.
Home-page: https://github.com/Divinemonk/justhacking/
Author: Divinemonk
Author-email: <v1b7rc8eb@relay.firefox.com>
License: UNKNOWN
Keywords: python,justhacking,divinemonk,hacking stimulation,cli,python hacking,console
Platform: UNKNOWN
Classifier: Programming Language :: Python :: 3
Classifier: Operating System :: Unix
Classifier: Operating System :: MacOS :: MacOS X
Classifier: License :: OSI Approved :: MIT License
Requires-Dist: rich
